Metadata-Version: 2.4
Name: llama-index-readers-slack
Version: 0.4.1
Summary: llama-index readers slack integration
Author-email: Your Name <you@example.com>
Maintainer: jerryjliu
License-Expression: MIT
License-File: LICENSE
Requires-Python: <4.0,>=3.9
Requires-Dist: llama-index-core<0.15,>=0.13.0
Requires-Dist: slack-sdk<4,>=3.26.2
